github_repo_extractor/__init__.py
github_repo_extractor/github_repo_extractor.py
github_repo_extractor-0.1.1.dist-info/LICENSE
github_repo_extractor-0.1.1.dist-info/METADATA
github_repo_extractor-0.1.1.dist-info/WHEEL
github_repo_extractor-0.1.1.dist-info/top_level.txt
github_repo_extractor-0.1.1.dist-info/RECORD
