Metadata-Version: 2.1
Name: github-repo-extractor
Version: 0.1.1
Summary: A tool to extract GitHub repositories into a single file
Home-page: https://github.com/ltoscano/github-repo-extractor
Author: Lorenzo Toscano
Author-email: lorenzo.toscano@gmail.com
Classifier: Development Status :: 3 - Alpha
Classifier: Intended Audience :: Developers
Classifier: License :: OSI Approved :: MIT License
Classifier: Operating System :: OS Independent
Classifier: Programming Language :: Python :: 3
Classifier: Programming Language :: Python :: 3.7
Classifier: Programming Language :: Python :: 3.8
Classifier: Programming Language :: Python :: 3.9
Requires-Python: >=3.7
License-File: LICENSE
Requires-Dist: pygithub
Requires-Dist: tqdm
Requires-Dist: gitpython
